rxss/__init__.py
rxss/rxss.py
rxss-0.0.2.dist-info/LICENSE
rxss-0.0.2.dist-info/METADATA
rxss-0.0.2.dist-info/WHEEL
rxss-0.0.2.dist-info/entry_points.txt
rxss-0.0.2.dist-info/top_level.txt
rxss-0.0.2.dist-info/RECORD
